sample_creator/__init__.py
sample_creator/categorical/__init__.py
sample_creator/categorical/combination.py
sample_creator/categorical/sampling.py
sample_creator/categorical/stratification.py
sample_creator/mixed/__init__.py
sample_creator/mixed/combination.py
sample_creator/mixed/sampling.py
sample_creator/mixed/stratification.py
sample_creator/numerical/__init__.py
sample_creator/numerical/combination.py
sample_creator/numerical/sampling.py
sample_creator/numerical/stratification.py
sample_creator/utils/__init__.py
sample_creator/utils/preprocessing.py
sample_creator-0.0.2.dist-info/METADATA
sample_creator-0.0.2.dist-info/WHEEL
sample_creator-0.0.2.dist-info/top_level.txt
sample_creator-0.0.2.dist-info/RECORD
