Metadata-Version: 2.1
Name: sample_creator
Version: 0.0.2
Summary: Representative sample creator
Author: SOM Research Lab
License: CC BY-SA
Project-URL: Source Code, https://github.com/SOM-Research/sample-creator
Project-URL: Bug Tracker, https://github.com/SOM-Research/sample-creator/issues
Keywords: sampling,representative samples
Requires-Python: >=3.9
Requires-Dist: matplotlib==3.9.0
Requires-Dist: numpy==1.26.4
Requires-Dist: pandas==2.2.2
Requires-Dist: scikit-learn==1.5.0
Requires-Dist: scipy==1.13.1
